get_danmu/__init__.py
get_danmu/__main__.py
get_danmu/config.py
get_danmu/core.py
get_danmu/api/__init__.py
get_danmu/api/danmu_bilibili.py
get_danmu/api/danmu_iqiyi.py
get_danmu/api/danmu_iqiyi_pro.py
get_danmu/api/danmu_mgtv.py
get_danmu/api/danmu_tx.py
get_danmu/api/danmu_youku.py
get_danmu/utils/__init__.py
get_danmu/utils/app.py
get_danmu/utils/danmu_iqiyi_pb2.py
get_danmu/utils/danmu_updata.py
get_danmu/utils/dm_pb2.py
get_danmu/utils/sqlite_orm.py
get_danmu/utils/update.py
get_danmu/utils/static/css/font-awesome/font-awesome.min.css
get_danmu/utils/static/css/fonts/fontawesome-webfont.eot
get_danmu/utils/static/css/fonts/fontawesome-webfont.ttf
get_danmu/utils/static/css/fonts/fontawesome-webfont.woff
get_danmu/utils/static/css/fonts/fontawesome-webfont.woff2
get_danmu/utils/static/js/chart.umd.min.js
get_danmu/utils/static/js/md5.min.js
get_danmu/utils/static/js/tailwindcss.js
get_danmu/utils/templates/admin.html
get_danmu/utils/templates/index.html
get_danmu/utils/templates/login.html
get_danmu-0.3.9.dist-info/LICENSE
get_danmu-0.3.9.dist-info/METADATA
get_danmu-0.3.9.dist-info/WHEEL
get_danmu-0.3.9.dist-info/entry_points.txt
get_danmu-0.3.9.dist-info/top_level.txt
get_danmu-0.3.9.dist-info/RECORD
