Metadata-Version: 2.1
Name: get-danmu
Version: 0.3.9
Summary: 可以下载弹幕的包哦
Home-page: 
Author: Li Zhan Qi
Author-email: 3101978435@qq.com
Classifier: Programming Language :: Python :: 3
Classifier: License :: OSI Approved :: GNU General Public License v3 (GPLv3)
Classifier: Operating System :: OS Independent
Classifier: Environment :: Console
Requires-Python: >=3.7
License-File: LICENSE
Requires-Dist: flask
Requires-Dist: flask-sqlalchemy
Requires-Dist: protobuf
Requires-Dist: requests
Requires-Dist: rich
Requires-Dist: sqlalchemy
Requires-Dist: ujson
Requires-Dist: lxml
Requires-Dist: prompt-toolkit
